arpeggia/__init__.py
arpeggia/arpeggia.cpython-310-aarch64-linux-gnu.so
arpeggia/arpeggia.pyi
arpeggia-0.7.0.dist-info/METADATA
arpeggia-0.7.0.dist-info/WHEEL
arpeggia-0.7.0.dist-info/licenses/LICENSE
arpeggia-0.7.0.dist-info/RECORD
