Metadata-Version: 2.4
Name: arpeggia
Version: 0.7.0
Classifier: Programming Language :: Rust
Classifier: Programming Language :: Python :: Implementation :: CPython
Classifier: Programming Language :: Python :: Implementation :: PyPy
Classifier: Programming Language :: Python :: 3
Classifier: Programming Language :: Python :: 3.10
Classifier: Programming Language :: Python :: 3.11
Classifier: Programming Language :: Python :: 3.12
Classifier: Programming Language :: Python :: 3.13
Classifier: Programming Language :: Python :: 3.14
Classifier: License :: OSI Approved :: MIT License
Classifier: Operating System :: OS Independent
Classifier: Topic :: Scientific/Engineering :: Bio-Informatics
Classifier: Topic :: Scientific/Engineering :: Chemistry
Requires-Dist: polars>=0.19.0,<2
Requires-Dist: pytest>=7.0 ; extra == 'dev'
Requires-Dist: maturin>=1.0 ; extra == 'dev'
Provides-Extra: dev
License-File: LICENSE
Summary: A library for analyzing protein-protein interactions in PDB and mmCIF files
Keywords: bioinformatics,structural-biology,pdb,protein-interactions
Author-email: Yi Zhou <me@y1zhou.com>
License: MIT
Requires-Python: >=3.10
Project-URL: Homepage, https://github.com/y1zhou/arpeggia
Project-URL: Issues, https://github.com/y1zhou/arpeggia/issues
Project-URL: Repository, https://github.com/y1zhou/arpeggia
